Metadata-Version: 1.1
Name: taiga-contrib-gitlab-auth
Version: 1.0.0
Summary: The Taiga plugin for gitlab authentication
Home-page: https://github.com/WedjaaOpen/taiga-contrib-gitlab-auth
Author: Fabio "MrWHO" Torchetti
Author-email: mrwho@wedjaa.net
License: AGPL
Download-URL: https://github.com/WedjaaOpen/taiga-contrib-gitlab-auth/tarball/1.0.0
Keywords: taiga,gitlab,auth,plugin
Platform: UNKNOWN
Classifier: Programming Language :: Python
Classifier: Development Status :: 5 - Production/Stable
Classifier: Framework :: Django
Classifier: Intended Audience :: Developers
Classifier: License :: OSI Approved :: GNU Affero General Public License v3
Classifier: Operating System :: OS Independent
Classifier: Programming Language :: Python
Classifier: Topic :: Internet :: WWW/HTTP
